MacTmp/__init__.py
MacTmp-0.0.9.dist-info/LICENSE
MacTmp-0.0.9.dist-info/METADATA
MacTmp-0.0.9.dist-info/WHEEL
MacTmp-0.0.9.dist-info/top_level.txt
MacTmp-0.0.9.dist-info/RECORD
