Metadata-Version: 2.1
Name: MacTmp
Version: 0.0.9
Summary: A package used to get temperatures on Mac OS Machines. 
Home-page: UNKNOWN
Author: Kethan
Author-email: kethan@vegunta.com
License: UNKNOWN
Platform: UNKNOWN
Classifier: Programming Language :: Python :: 3
Classifier: License :: OSI Approved :: MIT License
Classifier: Operating System :: MacOS
Requires-Python: >=3.3
